majorkirby/__init__.py
majorkirby/majorkirby.py
majorkirby-2.0.0.dist-info/licenses/LICENSE
majorkirby-2.0.0.dist-info/METADATA
majorkirby-2.0.0.dist-info/WHEEL
majorkirby-2.0.0.dist-info/top_level.txt
majorkirby-2.0.0.dist-info/RECORD
