Metadata-Version: 2.4
Name: majorkirby
Version: 2.0.0
Summary: Puts CloudFormation stacks into motion.
Author: Sharp Hall
Author-email: shall@azavea.com
Keywords: aws cloudformation
Classifier: Development Status :: 5 - Production/Stable
Classifier: Intended Audience :: Developers
Classifier: License :: OSI Approved :: Apache Software License
Classifier: Programming Language :: Python :: 3
Classifier: Programming Language :: Python :: 3.9
Classifier: Programming Language :: Python :: 3.10
Classifier: Programming Language :: Python :: 3.11
Classifier: Programming Language :: Python :: 3.12
License-File: LICENSE
Requires-Dist: troposphere>=0.7.2
Requires-Dist: boto3>=1.9.0
Provides-Extra: dev
Provides-Extra: test
Requires-Dist: moto[cloudformation]>=4.0.0; extra == "test"
Dynamic: author
Dynamic: author-email
Dynamic: classifier
Dynamic: keywords
Dynamic: license-file
Dynamic: provides-extra
Dynamic: requires-dist
Dynamic: summary
